budget/__init__.py
budget/cli.py
budget/commands/__init__.py
budget/commands/_options.py
budget/commands/balance.py
budget/commands/check.py
budget/console.py
budget/date.py
budget/hledger.py
budget/rendering/__init__.py
budget/rendering/_renderer.py
budget/rendering/csv.py
budget/rendering/jinja.py
budget/rendering/rich.py
budget/rendering/templates/__init__.py
budget/rendering/templates/dokuwiki.txt
budget/rendering/templates/html_bare.html
budget/rendering/templates/html_full.html
budget/rendering/templates/style.html
budget/structures.py
budget/table.py
budget/utils.py
hledger_budget-1.4.0.dist-info/LICENSE
hledger_budget-1.4.0.dist-info/METADATA
hledger_budget-1.4.0.dist-info/WHEEL
hledger_budget-1.4.0.dist-info/entry_points.txt
hledger_budget-1.4.0.dist-info/RECORD
