Metadata-Version: 2.3
Name: hledger-budget
Version: 1.4.0
Summary: Wrapper script for 'hledger balance --budget' report.
License: GPL-3.0
Author: Michal Goral
Author-email: dev@goral.net.pl
Requires-Python: >=3.10,<4.0
Classifier: License :: OSI Approved :: GNU General Public License v3 (GPLv3)
Classifier: Programming Language :: Python :: 3
Classifier: Programming Language :: Python :: 3.10
Classifier: Programming Language :: Python :: 3.11
Classifier: Programming Language :: Python :: 3.12
Classifier: Programming Language :: Python :: 3.13
Requires-Dist: click (>=8.1,<9.0)
Requires-Dist: importlib-metadata (>=4.0,<5.0) ; python_version < "3.8"
Requires-Dist: jinja2 (>=3.1.2,<4.0.0)
Requires-Dist: rich (>=13.7,<14.0)
